LICENSE
README.md
pyproject.toml
setup.py
lora/__init__.py
lora/crypto.py
lora/payload.py
python_lora.egg-info/PKG-INFO
python_lora.egg-info/SOURCES.txt
python_lora.egg-info/dependency_links.txt
python_lora.egg-info/requires.txt
python_lora.egg-info/top_level.txt